apscheduler/__init__.py
apscheduler/events.py
apscheduler/job.py
apscheduler/util.py
apscheduler/executors/__init__.py
apscheduler/executors/asyncio.py
apscheduler/executors/base.py
apscheduler/executors/base_py3.py
apscheduler/executors/debug.py
apscheduler/executors/gevent.py
apscheduler/executors/pool.py
apscheduler/executors/tornado.py
apscheduler/executors/twisted.py
apscheduler/jobstores/__init__.py
apscheduler/jobstores/base.py
apscheduler/jobstores/memory.py
apscheduler/jobstores/mongodb.py
apscheduler/jobstores/redis.py
apscheduler/jobstores/rethinkdb.py
apscheduler/jobstores/sqlalchemy.py
apscheduler/jobstores/zookeeper.py
apscheduler/schedulers/__init__.py
apscheduler/schedulers/asyncio.py
apscheduler/schedulers/background.py
apscheduler/schedulers/base.py
apscheduler/schedulers/blocking.py
apscheduler/schedulers/gevent.py
apscheduler/schedulers/qt.py
apscheduler/schedulers/tornado.py
apscheduler/schedulers/twisted.py
apscheduler/triggers/__init__.py
apscheduler/triggers/base.py
apscheduler/triggers/combining.py
apscheduler/triggers/date.py
apscheduler/triggers/interval.py
apscheduler/triggers/cron/__init__.py
apscheduler/triggers/cron/expressions.py
apscheduler/triggers/cron/fields.py
APScheduler-3.10.2.dist-info/LICENSE.txt
APScheduler-3.10.2.dist-info/METADATA
APScheduler-3.10.2.dist-info/WHEEL
APScheduler-3.10.2.dist-info/entry_points.txt
APScheduler-3.10.2.dist-info/top_level.txt
APScheduler-3.10.2.dist-info/RECORD
