Metadata-Version: 2.1
Name: APScheduler
Version: 3.10.2
Summary: In-process task scheduler with Cron-like capabilities
Home-page: https://github.com/agronholm/apscheduler
Author: Alex Grönholm
Author-email: apscheduler@nextday.fi
License: MIT
Keywords: scheduling cron
Classifier: Development Status :: 5 - Production/Stable
Classifier: Intended Audience :: Developers
Classifier: License :: OSI Approved :: MIT License
Classifier: Programming Language :: Python
Classifier: Programming Language :: Python :: 3
Classifier: Programming Language :: Python :: 3.6
Classifier: Programming Language :: Python :: 3.7
Classifier: Programming Language :: Python :: 3.8
Classifier: Programming Language :: Python :: 3.9
Classifier: Programming Language :: Python :: 3.10
Classifier: Programming Language :: Python :: 3.11
Requires-Python: >=3.6
Provides-Extra: gevent
Provides-Extra: mongodb
Provides-Extra: redis
Provides-Extra: rethinkdb
Provides-Extra: sqlalchemy
Provides-Extra: tornado
Provides-Extra: twisted
Provides-Extra: zookeeper
Provides-Extra: testing
Provides-Extra: doc
License-File: LICENSE.txt
